isJem3a/__init__.py
isJem3a/check.py
isJem3a-1.0.0.dist-info/LICENSE
isJem3a-1.0.0.dist-info/METADATA
isJem3a-1.0.0.dist-info/WHEEL
isJem3a-1.0.0.dist-info/entry_points.txt
isJem3a-1.0.0.dist-info/top_level.txt
isJem3a-1.0.0.dist-info/RECORD
